{"status": 0, "amq": {"date": null, "status": 0, "resp": null, "req": [[], [], []], "nofact": "86"}, "cas": null, "ins": {"status": 3, "info": {"Ass": "MED", "Nom": "PLOURDE", "Prenom": "MALIA"}, "transaction": "HD*         0609670202000036FM201330521810005957601306            0003869241 3PLOURDE                  MICHAEL                       ", "resp": "60967,0,000,22211111    060967022100006004640583179003359171666197A    000000000019800F011040017800000000          100000000000000000000010000000012332201980000000090017800020101 - LA COASSURANCE A ?T? AJUST?E POUR REFL?TER LE MONTANT DE LA                PRESTATION.                                                           02 - Le code de proc?dure soumis a ?t? modifi? pour refl?ter le syst?me de      codification de l'Association dentaire canadienne.                    ", "req": [{"Honoraires": "54.00", "Code": "21211", "Description": "AMALGAME CONVENTIONNEL, ANTERIEURE PERMA", "Frais": "0.00", "codeRole": "", "Surface": "B", "Dent": "33", "Total": "54.00", "row_id": "1", "Prod": "1", "Type": "MED", "undefined": "PlusSupprimer"}, {"Honoraires": "54.00", "Code": "21211", "Description": "AMALGAME CONVENTIONNEL, ANTERIEURE PERMA", "Frais": "0.00", "codeRole": "", "Surface": "M", "Dent": "13", "Total": "54.00", "row_id": "2", "Prod": "1", "Type": "MED", "undefined": "PlusSupprimer"}], "nofact": "86", "date": "2018-01-31 15:02:46"}}